<?xml version="1.0" encoding="UTF-8"?><record_update table="sp_instance">
    <sp_instance action="INSERT_OR_UPDATE">
        <active>true</active>
        <class_name/>
        <color>default</color>
        <css/>
        <glyph/>
        <id/>
        <order>1</order>
        <roles/>
        <short_description/>
        <size>md</size>
        <sp_column display_value="1">1ae61d80db160010ea5188094896194b</sp_column>
        <sp_widget display_value="My widget 3">a82d11c0db160010ea518809489619cd</sp_widget>
        <sys_class_name>sp_instance</sys_class_name>
        <sys_created_by>admin</sys_created_by>
        <sys_created_on>2020-01-07 14:08:08</sys_created_on>
        <sys_id>2a7dd980db160010ea51880948961988</sys_id>
        <sys_mod_count>1</sys_mod_count>
        <sys_name/>
        <sys_package display_value="CreateNotes" source="x_snc_createnotes">df5fd9a5090232007f44e1046c8ff69f</sys_package>
        <sys_policy/>
        <sys_scope display_value="CreateNotes">df5fd9a5090232007f44e1046c8ff69f</sys_scope>
        <sys_update_name>sp_instance_2a7dd980db160010ea51880948961988</sys_update_name>
        <sys_updated_by>admin</sys_updated_by>
        <sys_updated_on>2020-01-07 14:08:15</sys_updated_on>
        <title/>
        <url/>
        <widget_parameters/>
    </sp_instance>
    <sys_translated_text action="delete_multiple" query="documentkey=2a7dd980db160010ea51880948961988"/>
</record_update>
